hassle/__init__.py
hassle/hassle_cli.py
hassle/models.py
hassle/parsers.py
hassle/py.typed
hassle/utilities.py
hassle/templates/.gitignore.txt
hassle/templates/README.md
hassle/templates/license.txt
hassle/templates/pyproject.toml
hassle/templates/vscode_settings.json
hassle-3.1.10.dist-info/METADATA
hassle-3.1.10.dist-info/WHEEL
hassle-3.1.10.dist-info/entry_points.txt
hassle-3.1.10.dist-info/licenses/LICENSE.txt
hassle-3.1.10.dist-info/RECORD
