Metadata-Version: 2.4
Name: hassle
Version: 3.1.10
Summary: Create, build, test, and publish Python projects and packages.
Project-URL: Homepage, https://github.com/matt-manes/hassle
Project-URL: Documentation, https://github.com/matt-manes/hassle/tree/main/docs
Project-URL: Source code, https://github.com/matt-manes/hassle/tree/main/src/hassle
Author-email: Matt Manes <mattmanes@pm.me>
License-File: LICENSE.txt
Keywords: automation,build,devops,packaging,test
Classifier: License :: OSI Approved :: MIT License
Classifier: Operating System :: OS Independent
Classifier: Programming Language :: Python :: 3
Requires-Python: <3.12,>=3.10
Requires-Dist: argshell
Requires-Dist: auto-changelog
Requires-Dist: beautifulsoup4
Requires-Dist: black
Requires-Dist: bs4
Requires-Dist: build
Requires-Dist: coverage
Requires-Dist: dacite
Requires-Dist: gitbetter
Requires-Dist: isort
Requires-Dist: packagelister
Requires-Dist: pathier
Requires-Dist: pdoc
Requires-Dist: pip
Requires-Dist: pytest~=7.2.1
Requires-Dist: requests
Requires-Dist: twine
Requires-Dist: typing-extensions
